qobuz/__init__.py
qobuz/album.py
qobuz/api.py
qobuz/artist.py
qobuz/event.py
qobuz/playlist.py
qobuz/track.py
qobuz/user.py
qobuz-0.0.2.dist-info/LICENSE
qobuz-0.0.2.dist-info/METADATA
qobuz-0.0.2.dist-info/WHEEL
qobuz-0.0.2.dist-info/top_level.txt
qobuz-0.0.2.dist-info/RECORD
