Metadata-Version: 2.1
Name: qobuz
Version: 0.0.2
Summary: "Unoffical API for Qobuz music streaming service."
Home-page: https://github.com/taschenb/python-qobuz
Author: taschenb
Author-email: taschenb@posteo.de
License: MIT
Keywords: qobuz,music,streaming
Platform: UNKNOWN
Classifier: License :: OSI Approved :: MIT License
Classifier: Programming Language :: Python
Classifier: Programming Language :: Python :: 2
Classifier: Programming Language :: Python :: 2.7
Classifier: Programming Language :: Python :: 3
Classifier: Programming Language :: Python :: 3.4
Classifier: Programming Language :: Python :: 3.5
Classifier: Programming Language :: Python :: 3.6
Classifier: Programming Language :: Python :: 3.7
Requires-Dist: requests (>=2.11.1)
Provides-Extra: develop
Requires-Dist: flake8 ; extra == 'develop'
Requires-Dist: pytest ; extra == 'develop'
Requires-Dist: coverage ; extra == 'develop'
Requires-Dist: responses ; extra == 'develop'
Provides-Extra: test
Requires-Dist: pytest ; extra == 'test'
Requires-Dist: responses ; extra == 'test'
